hippiepug/__init__.py
hippiepug/_meta.py
hippiepug/chain.py
hippiepug/pack.py
hippiepug/store.py
hippiepug/struct.py
hippiepug/tree.py
hippiepug-0.4.2.dist-info/METADATA
hippiepug-0.4.2.dist-info/RECORD
hippiepug-0.4.2.dist-info/WHEEL
hippiepug-0.4.2.dist-info/top_level.txt
