Metadata-Version: 2.1
Name: hippiepug
Version: 0.4.2
Summary: Sublinear-lookup blockchains and efficient key-value Merkle trees with a flexible storage backend
Home-page: https://github.com/spring-epfl/hippiepug
Author: Bogdan Kulynych
Author-email: hello@bogdankulynych.me
License: MIT
Platform: UNKNOWN
Classifier: Development Status :: 3 - Alpha
Classifier: Intended Audience :: Developers
Classifier: Natural Language :: English
Classifier: Operating System :: OS Independent
Classifier: Programming Language :: Python
Classifier: Programming Language :: Python :: 2
Classifier: Programming Language :: Python :: 2.7
Classifier: Programming Language :: Python :: 3
Classifier: Programming Language :: Python :: 3.4
Classifier: Programming Language :: Python :: 3.5
Classifier: Programming Language :: Python :: 3.6
Classifier: Programming Language :: Python :: Implementation :: CPython
Classifier: Topic :: Software Development :: Libraries :: Python Modules
Classifier: Topic :: Security :: Cryptography
Classifier: Topic :: Database
Classifier: License :: OSI Approved :: MIT License
Requires-Dist: attrs (>=17.4.0)
Requires-Dist: msgpack (>=0.5.6)
Requires-Dist: defaultcontext (>=1.1.0)
Provides-Extra: dev
Requires-Dist: pytest; extra == 'dev'
Requires-Dist: mock; extra == 'dev'
Requires-Dist: pytest-lazy-fixture; extra == 'dev'
Requires-Dist: sphinx; extra == 'dev'
Requires-Dist: sphinx-rtd-theme; extra == 'dev'
Provides-Extra: test
Requires-Dist: pytest; extra == 'test'
Requires-Dist: mock; extra == 'test'
Requires-Dist: pytest-lazy-fixture; extra == 'test'
